PyA2Z/__init__.py
PyA2Z/measure.py
pya2z-0.0.2.dist-info/METADATA
pya2z-0.0.2.dist-info/WHEEL
pya2z-0.0.2.dist-info/licenses/LICENSE
pya2z-0.0.2.dist-info/RECORD
