Metadata-Version: 2.3
Name: PyA2Z
Version: 0.0.2
Summary: PyA2Z: python for asteroseismic global analysis
Project-URL: Homepage, https://github.com/BLiagre/PyA2Z
Project-URL: Issues, https://github.com/BLiagre/PyA2Z
Author-email: Bastien Liagre <bastienliagre@hotmail.fr>
License-File: LICENSE
Classifier: License :: OSI Approved :: GNU General Public License v3 or later (GPLv3+)
Classifier: Operating System :: OS Independent
Classifier: Programming Language :: Python :: 3
Requires-Python: >=3.8
